PIKM_Inpainter/Algorithm.py
PIKM_Inpainter/Image.py
PIKM_Inpainter/Mask.py
PIKM_Inpainter/__init__.py
PIKM_Inpainter/experiments.py
PIKM_Inpainter/getInpainted.py
PIKM_Inpainter-0.0.2.dist-info/LICENSE
PIKM_Inpainter-0.0.2.dist-info/METADATA
PIKM_Inpainter-0.0.2.dist-info/WHEEL
PIKM_Inpainter-0.0.2.dist-info/top_level.txt
PIKM_Inpainter-0.0.2.dist-info/RECORD
