Metadata-Version: 2.1
Name: PIKM_Inpainter
Version: 0.0.2
Summary: A small package to inpaint pictures according to perturbed inertial Krasnoselskii-Mann iterations.
Author-email: Daniel Cortild <d.cortild@rug.nl>
Project-URL: Homepage, https://github.com/DanielCortild/PIKM-Image-Inpainting
Project-URL: Bug Tracker, https://github.com/DanielCortild/PIKM-Image-Inpainting/issues
Classifier: Programming Language :: Python :: 3
Classifier: License :: OSI Approved :: MIT License
Classifier: Operating System :: OS Independent
Requires-Python: >=3.7
License-File: LICENSE
